setup.py
TGCode.egg-info/PKG-INFO
TGCode.egg-info/SOURCES.txt
TGCode.egg-info/dependency_links.txt
TGCode.egg-info/top_level.txt
tgcode/__init__.py