Metadata-Version: 1.0
Name: TGCode
Version: 0.3.0.post2
Summary: TGCode is a simple library that let's you convert binary data into a string and vice-versa.
Home-page: UNKNOWN
Author: thegamerbr1
Author-email: xthegamerbr1x@gmail.com
License: MIT
Keywords: encoding binary bytes string data irc file bin convert
Platform: UNKNOWN
